caeops/__init__.py
caeops/__main__.py
caeops/config.json
caeops/configurations.py
caeops/global_settings.py
caeops/main.py
caeops/storage.py
caeops/utilities.py
caeops/common/__init__.py
caeops/common/api_helper.py
caeops/common/file_input_helper.py
caeops/common/get_tenant.py
caeops/common/get_user.py
caeops/common/labels_format.py
caeops/common/parser.py
caeops/common/validators.py
caeops/services/__init__.py
caeops/services/dashboards/__init__.py
caeops/services/dashboards/add_labels.py
caeops/services/dashboards/create.py
caeops/services/dashboards/delete.py
caeops/services/dashboards/delete_labels.py
caeops/services/dashboards/get.py
caeops/services/dashboards/get_labels.py
caeops/services/dashboards/list.py
caeops/services/groups/__init__.py
caeops/services/groups/add_users.py
caeops/services/groups/list.py
caeops/services/groups/list_users.py
caeops/services/groups/remove_users.py
caeops/services/logs/__init__.py
caeops/services/logs/add_labels.py
caeops/services/logs/add_to_group.py
caeops/services/logs/create_elastic_domain.py
caeops/services/logs/create_parsing_rule.py
caeops/services/logs/delete_elastic_domain.py
caeops/services/logs/delete_labels.py
caeops/services/logs/delete_parsing_rule.py
caeops/services/logs/describe_elastic_domain.py
caeops/services/logs/disable_parsing_rule.py
caeops/services/logs/enable_parsing_rule.py
caeops/services/logs/get_labels.py
caeops/services/logs/get_parsing_rule.py
caeops/services/logs/install_agent.py
caeops/services/logs/list_elastic_domain.py
caeops/services/logs/list_parsing_rules.py
caeops/services/logs/remove_from_group.py
caeops/services/logs/update_agent.py
caeops/services/logs/update_parsing_rule.py
caeops/services/logs_analyzers/__init__.py
caeops/services/logs_analyzers/create.py
caeops/services/logs_analyzers/delete.py
caeops/services/logs_analyzers/get.py
caeops/services/logs_analyzers/list.py
caeops/services/logs_analyzers/update.py
caeops/services/metrics/__init__.py
caeops-0.0.7.dist-info/METADATA
caeops-0.0.7.dist-info/WHEEL
caeops-0.0.7.dist-info/entry_points.txt
caeops-0.0.7.dist-info/top_level.txt
caeops-0.0.7.dist-info/RECORD
